examples/__init__.py
examples/autosampler.py
sielc_dompser/__init__.py
sielc_dompser/__version__.py
sielc_dompser/autosampler/__init__.py
sielc_dompser/autosampler/autosampler.py
sielc_dompser-0.6.0.dist-info/LICENSE
sielc_dompser-0.6.0.dist-info/METADATA
sielc_dompser-0.6.0.dist-info/WHEEL
sielc_dompser-0.6.0.dist-info/top_level.txt
sielc_dompser-0.6.0.dist-info/RECORD
