Metadata-Version: 2.1
Name: sielc-dompser
Version: 0.6.0
Summary: This is an unofficial Python package to interface with SIELC Technologies, Inc products through DOMP (Device Objected Manager Protocol) serial communication. We are not affiliated with SIELC.
Home-page: https://gitlab.com/heingroup/sielc_dompser
Author: Veronica Lai // Hein Group
Author-email: 
Requires-Python: >=3.6
License-File: LICENSE
Requires-Dist: ftdi-serial
